{
  "id":"dc-united",
  "country":"US",
  "name":"DC United",
  "seasons":[{
    "year":"2016",
    "league":"mls",
    "manufacturer":"Adidas",
    "kits":[
      {
        "type":"Primary",
        "design":"solid",
        "colors":["1B181F"],
        "sponsor":"leidos",
        "sponsorColor":"FFFFFF"      
      },
      {
        "type":"Away",
        "colors":["860009","FFFFFF"],
        "design":"gradient",
        "sponsor":"leidos",
        "sponsorColor":"000000"
      }
    ]
  }]
}